tests/__init__.py
utils/__init__.py
utils/component.py
utils/constants.py
utils/project_structure.py
fastapi_project_cli-1.0.0.dist-info/LICENSE
fastapi_project_cli-1.0.0.dist-info/METADATA
fastapi_project_cli-1.0.0.dist-info/WHEEL
fastapi_project_cli-1.0.0.dist-info/entry_points.txt
fastapi_project_cli-1.0.0.dist-info/top_level.txt
fastapi_project_cli-1.0.0.dist-info/RECORD
